needinit/__init__.py
needinit/_version.py
needinit-0.2.1.dist-info/DESCRIPTION.rst
needinit-0.2.1.dist-info/METADATA
needinit-0.2.1.dist-info/RECORD
needinit-0.2.1.dist-info/WHEEL
needinit-0.2.1.dist-info/metadata.json
needinit-0.2.1.dist-info/top_level.txt
