Metadata-Version: 2.0
Name: needinit
Version: 0.2.1
Summary: Prevent callability on un-initialized objects
Home-page: https://github.com/steinnes/needinit
Author: Steinn Eldjarn Sigurdarson
Author-email: steinnes@gmail.com
License: UNKNOWN
Keywords: library,object initialization
Platform: UNKNOWN
